Metadata-Version: 2.1
Name: huntress
Version: 0.0.1
Summary: Educational package about throwing hatchets and learning how to push code to PyPi
Home-page: https://github.com/sillyfatcat/huntress
Author: stupidfatcat
Author-email: sshum@stupidfatcat.com
License: MIT
Download-URL: https://github.com/sillyfatcat/huntress/archive/v0.1.tar.gz
Keywords: EDUCATIONAL
Platform: UNKNOWN
Classifier: Development Status :: 4 - Beta
Classifier: Intended Audience :: Developers
Classifier: Topic :: Games/Entertainment
Classifier: License :: OSI Approved :: MIT License
Classifier: Programming Language :: Python :: 3
Classifier: Programming Language :: Python :: 3.4
Classifier: Programming Language :: Python :: 3.5
Classifier: Programming Language :: Python :: 3.6
Classifier: Programming Language :: Python :: 3.7
Classifier: Programming Language :: Python :: 3.8
